flowrider-0.1.3.dist-info/METADATA
flowrider-0.1.3.dist-info/WHEEL
flowrider-0.1.3.dist-info/licenses/LICENSE
flowrider.libs/libgcc_s-e52197c3.so.1
flowrider/__init__.py
flowrider/flowrider.cpython-311-aarch64-linux-musl.so
flowrider-0.1.3.dist-info/RECORD
